{
  "dictionaries": [],
  "dictionaryDefinitions": [],
  "ignorePaths": [],
  "ignoreWords": [],
  "import": [],
  "version": "0.2",
  "words": [
    "addresschain",
    "addresshistory",
    "Arie",
    "arietrouw",
    "ARIMA",
    "Autopurge",
    "Autoregressive",
    "bitauth",
    "boundwitness",
    "boundwtness",
    "codacy",
    "codeclimate",
    "coinapp",
    "composability",
    "cryptomarket",
    "decentralnetworkservices",
    "deregistering",
    "deregisters",
    "dotenv",
    "emittery",
    "ethgasstation",
    "Evaluable",
    "geomines",
    "GLTF",
    "gten",
    "hashable",
    "Hasher",
    "hdnode",
    "healthz",
    "huri",
    "IDBP",
    "indexeddb",
    "Initializable",
    "initializables",
    "interoperably",
    "IPFS",
    "IXSCAN",
    "jsdom",
    "keccak",
    "keypair",
    "libauth",
    "lognormal",
    "malleate",
    "malleation",
    "Matroska",
    "Merkle",
    "microether",
    "milliether",
    "pako",
    "Promisable",
    "quicktime",
    "realvideo",
    "replicaset",
    "satoshi",
    "scrollback",
    "Secp",
    "snyk",
    "systeminfo",
    "Trouw",
    "typedoc",
    "wordlists",
    "xylabs",
    "yarnpkg"
  ]
}
